{
  "kind": "collectionType",
  "collectionName": "commandes",
  "info": {
    "singularName": "commande",
    "pluralName": "commandes",
    "displayName": "commande",
    "description": ""
  },
  "options": {
    "draftAndPublish": true
  },
  "pluginOptions": {},
  "attributes": {
    "nom": {
      "type": "string",
      "required": true
    },
    "prenom": {
      "type": "string",
      "required": true
    },
    "email": {
      "type": "email",
      "required": true
    },
    "adresse": {
      "type": "text",
      "required": true
    },
    "prix_total": {
      "type": "float",
      "required": true
    },
    "produits": {
      "type": "json",
      "required": true
    },
    "date": {
      "type": "datetime",
      "required": true
    },
    "paymentIntent": {
      "type": "string",
      "required": true,
      "unique": true,
      "private": true
    },
    "paymentConfirmed": {
      "type": "boolean",
      "default": false,
      "required": true,
      "private": true
    }
  }
}
